{"frames":[{"filename":"play0009","frame":{"x":0,"y":0,"w":257,"h":219},"rotated":false,"trimmed":false,"spriteSourceSize":{"x":0,"y":0,"w":257,"h":219},"sourceSize":{"w":257,"h":219}},{"filename":"play0010","frame":{"x":0,"y":220,"w":257,"h":219},"rotated":false,"trimmed":false,"spriteSourceSize":{"x":0,"y":0,"w":257,"h":219},"sourceSize":{"w":257,"h":219}},{"filename":"play0011","frame":{"x":258,"y":0,"w":257,"h":219},"rotated":false,"trimmed":false,"spriteSourceSize":{"x":0,"y":0,"w":257,"h":219},"sourceSize":{"w":257,"h":219}},{"filename":"play0012","frame":{"x":258,"y":220,"w":257,"h":219},"rotated":false,"trimmed":false,"spriteSourceSize":{"x":0,"y":0,"w":257,"h":219},"sourceSize":{"w":257,"h":219}},{"filename":"play0013","frame":{"x":0,"y":440,"w":257,"h":219},"rotated":false,"trimmed":false,"spriteSourceSize":{"x":0,"y":0,"w":257,"h":219},"sourceSize":{"w":257,"h":219}},{"filename":"play0014","frame":{"x":258,"y":440,"w":257,"h":219},"rotated":false,"trimmed":false,"spriteSourceSize":{"x":0,"y":0,"w":257,"h":219},"sourceSize":{"w":257,"h":219}},{"filename":"play0015","frame":{"x":516,"y":0,"w":257,"h":219},"rotated":false,"trimmed":false,"spriteSourceSize":{"x":0,"y":0,"w":257,"h":219},"sourceSize":{"w":257,"h":219}},{"filename":"play0016","frame":{"x":516,"y":220,"w":257,"h":219},"rotated":false,"trimmed":false,"spriteSourceSize":{"x":0,"y":0,"w":257,"h":219},"sourceSize":{"w":257,"h":219}},{"filename":"play0017","frame":{"x":516,"y":440,"w":257,"h":219},"rotated":false,"trimmed":false,"spriteSourceSize":{"x":0,"y":0,"w":257,"h":219},"sourceSize":{"w":257,"h":219}},{"filename":"play0018","frame":{"x":0,"y":660,"w":257,"h":219},"rotated":false,"trimmed":false,"spriteSourceSize":{"x":0,"y":0,"w":257,"h":219},"sourceSize":{"w":257,"h":219}},{"filename":"play0019","frame":{"x":258,"y":660,"w":257,"h":219},"rotated":false,"trimmed":false,"spriteSourceSize":{"x":0,"y":0,"w":257,"h":219},"sourceSize":{"w":257,"h":219}},{"filename":"play0020","frame":{"x":516,"y":660,"w":257,"h":219},"rotated":false,"trimmed":false,"spriteSourceSize":{"x":0,"y":0,"w":257,"h":219},"sourceSize":{"w":257,"h":219}},{"filename":"play0021","frame":{"x":774,"y":0,"w":257,"h":219},"rotated":false,"trimmed":false,"spriteSourceSize":{"x":0,"y":0,"w":257,"h":219},"sourceSize":{"w":257,"h":219}},{"filename":"play0022","frame":{"x":774,"y":220,"w":257,"h":219},"rotated":false,"trimmed":false,"spriteSourceSize":{"x":0,"y":0,"w":257,"h":219},"sourceSize":{"w":257,"h":219}},{"filename":"hover","frame":{"x":774,"y":440,"w":257,"h":219},"rotated":false,"trimmed":false,"spriteSourceSize":{"x":0,"y":0,"w":257,"h":219},"sourceSize":{"w":257,"h":219}},{"filename":"idle","frame":{"x":774,"y":660,"w":257,"h":219},"rotated":false,"trimmed":false,"spriteSourceSize":{"x":0,"y":0,"w":257,"h":219},"sourceSize":{"w":257,"h":219}},{"filename":"play0000","frame":{"x":0,"y":880,"w":257,"h":219},"rotated":false,"trimmed":false,"spriteSourceSize":{"x":0,"y":0,"w":257,"h":219},"sourceSize":{"w":257,"h":219}},{"filename":"play0001","frame":{"x":258,"y":880,"w":257,"h":219},"rotated":false,"trimmed":false,"spriteSourceSize":{"x":0,"y":0,"w":257,"h":219},"sourceSize":{"w":257,"h":219}},{"filename":"play0002","frame":{"x":516,"y":880,"w":257,"h":219},"rotated":false,"trimmed":false,"spriteSourceSize":{"x":0,"y":0,"w":257,"h":219},"sourceSize":{"w":257,"h":219}},{"filename":"play0003","frame":{"x":774,"y":880,"w":257,"h":219},"rotated":false,"trimmed":false,"spriteSourceSize":{"x":0,"y":0,"w":257,"h":219},"sourceSize":{"w":257,"h":219}},{"filename":"play0004","frame":{"x":1032,"y":0,"w":257,"h":219},"rotated":false,"trimmed":false,"spriteSourceSize":{"x":0,"y":0,"w":257,"h":219},"sourceSize":{"w":257,"h":219}},{"filename":"play0005","frame":{"x":1032,"y":220,"w":257,"h":219},"rotated":false,"trimmed":false,"spriteSourceSize":{"x":0,"y":0,"w":257,"h":219},"sourceSize":{"w":257,"h":219}},{"filename":"play0006","frame":{"x":1032,"y":440,"w":257,"h":219},"rotated":false,"trimmed":false,"spriteSourceSize":{"x":0,"y":0,"w":257,"h":219},"sourceSize":{"w":257,"h":219}},{"filename":"play0007","frame":{"x":1032,"y":660,"w":257,"h":219},"rotated":false,"trimmed":false,"spriteSourceSize":{"x":0,"y":0,"w":257,"h":219},"sourceSize":{"w":257,"h":219}},{"filename":"play0008","frame":{"x":1032,"y":880,"w":257,"h":219},"rotated":false,"trimmed":false,"spriteSourceSize":{"x":0,"y":0,"w":257,"h":219},"sourceSize":{"w":257,"h":219}}],"meta":{"app":"https://www.leshylabs.com/apps/sstool/","version":"Leshy SpriteSheet Tool v0.8.4","image":"horn.png","size":{"w":1289,"h":1099},"scale":1}}