{"frames":[{"filename":"heat0002","frame":{"x":0,"y":0,"w":1791,"h":159},"rotated":false,"trimmed":false,"spriteSourceSize":{"x":0,"y":0,"w":1791,"h":159},"sourceSize":{"w":1791,"h":159}},{"filename":"heat0003","frame":{"x":0,"y":160,"w":1791,"h":159},"rotated":false,"trimmed":false,"spriteSourceSize":{"x":0,"y":0,"w":1791,"h":159},"sourceSize":{"w":1791,"h":159}},{"filename":"heat0004","frame":{"x":0,"y":320,"w":1791,"h":159},"rotated":false,"trimmed":false,"spriteSourceSize":{"x":0,"y":0,"w":1791,"h":159},"sourceSize":{"w":1791,"h":159}},{"filename":"heat0005","frame":{"x":0,"y":480,"w":1791,"h":159},"rotated":false,"trimmed":false,"spriteSourceSize":{"x":0,"y":0,"w":1791,"h":159},"sourceSize":{"w":1791,"h":159}},{"filename":"heat0006","frame":{"x":0,"y":640,"w":1791,"h":159},"rotated":false,"trimmed":false,"spriteSourceSize":{"x":0,"y":0,"w":1791,"h":159},"sourceSize":{"w":1791,"h":159}},{"filename":"heat0007","frame":{"x":0,"y":800,"w":1791,"h":159},"rotated":false,"trimmed":false,"spriteSourceSize":{"x":0,"y":0,"w":1791,"h":159},"sourceSize":{"w":1791,"h":159}},{"filename":"heat0008","frame":{"x":0,"y":960,"w":1791,"h":159},"rotated":false,"trimmed":false,"spriteSourceSize":{"x":0,"y":0,"w":1791,"h":159},"sourceSize":{"w":1791,"h":159}},{"filename":"heat0009","frame":{"x":0,"y":1120,"w":1791,"h":159},"rotated":false,"trimmed":false,"spriteSourceSize":{"x":0,"y":0,"w":1791,"h":159},"sourceSize":{"w":1791,"h":159}},{"filename":"heat0010","frame":{"x":0,"y":1280,"w":1791,"h":159},"rotated":false,"trimmed":false,"spriteSourceSize":{"x":0,"y":0,"w":1791,"h":159},"sourceSize":{"w":1791,"h":159}},{"filename":"heat0011","frame":{"x":0,"y":1440,"w":1791,"h":159},"rotated":false,"trimmed":false,"spriteSourceSize":{"x":0,"y":0,"w":1791,"h":159},"sourceSize":{"w":1791,"h":159}},{"filename":"heat0012","frame":{"x":0,"y":1600,"w":1791,"h":159},"rotated":false,"trimmed":false,"spriteSourceSize":{"x":0,"y":0,"w":1791,"h":159},"sourceSize":{"w":1791,"h":159}},{"filename":"heat0013","frame":{"x":0,"y":1760,"w":1791,"h":159},"rotated":false,"trimmed":false,"spriteSourceSize":{"x":0,"y":0,"w":1791,"h":159},"sourceSize":{"w":1791,"h":159}},{"filename":"heat0014","frame":{"x":0,"y":1920,"w":1791,"h":159},"rotated":false,"trimmed":false,"spriteSourceSize":{"x":0,"y":0,"w":1791,"h":159},"sourceSize":{"w":1791,"h":159}},{"filename":"heat0015","frame":{"x":0,"y":2080,"w":1791,"h":159},"rotated":false,"trimmed":false,"spriteSourceSize":{"x":0,"y":0,"w":1791,"h":159},"sourceSize":{"w":1791,"h":159}},{"filename":"heat0017","frame":{"x":0,"y":2240,"w":1791,"h":159},"rotated":false,"trimmed":false,"spriteSourceSize":{"x":0,"y":0,"w":1791,"h":159},"sourceSize":{"w":1791,"h":159}},{"filename":"heat0021","frame":{"x":0,"y":2400,"w":1791,"h":159},"rotated":false,"trimmed":false,"spriteSourceSize":{"x":0,"y":0,"w":1791,"h":159},"sourceSize":{"w":1791,"h":159}},{"filename":"heat0018","frame":{"x":0,"y":2560,"w":1791,"h":159},"rotated":false,"trimmed":false,"spriteSourceSize":{"x":0,"y":0,"w":1791,"h":159},"sourceSize":{"w":1791,"h":159}},{"filename":"heat0020","frame":{"x":0,"y":2720,"w":1791,"h":159},"rotated":false,"trimmed":false,"spriteSourceSize":{"x":0,"y":0,"w":1791,"h":159},"sourceSize":{"w":1791,"h":159}},{"filename":"heat0016","frame":{"x":0,"y":2880,"w":1791,"h":159},"rotated":false,"trimmed":false,"spriteSourceSize":{"x":0,"y":0,"w":1791,"h":159},"sourceSize":{"w":1791,"h":159}},{"filename":"heat0022","frame":{"x":0,"y":3040,"w":1791,"h":159},"rotated":false,"trimmed":false,"spriteSourceSize":{"x":0,"y":0,"w":1791,"h":159},"sourceSize":{"w":1791,"h":159}},{"filename":"heat0019","frame":{"x":0,"y":3200,"w":1791,"h":159},"rotated":false,"trimmed":false,"spriteSourceSize":{"x":0,"y":0,"w":1791,"h":159},"sourceSize":{"w":1791,"h":159}},{"filename":"heat0023","frame":{"x":0,"y":3360,"w":1791,"h":159},"rotated":false,"trimmed":false,"spriteSourceSize":{"x":0,"y":0,"w":1791,"h":159},"sourceSize":{"w":1791,"h":159}},{"filename":"heat0024","frame":{"x":1792,"y":0,"w":1791,"h":159},"rotated":false,"trimmed":false,"spriteSourceSize":{"x":0,"y":0,"w":1791,"h":159},"sourceSize":{"w":1791,"h":159}},{"filename":"heat0025","frame":{"x":1792,"y":160,"w":1791,"h":159},"rotated":false,"trimmed":false,"spriteSourceSize":{"x":0,"y":0,"w":1791,"h":159},"sourceSize":{"w":1791,"h":159}},{"filename":"heat0026","frame":{"x":1792,"y":320,"w":1791,"h":159},"rotated":false,"trimmed":false,"spriteSourceSize":{"x":0,"y":0,"w":1791,"h":159},"sourceSize":{"w":1791,"h":159}},{"filename":"heat0027","frame":{"x":1792,"y":480,"w":1791,"h":159},"rotated":false,"trimmed":false,"spriteSourceSize":{"x":0,"y":0,"w":1791,"h":159},"sourceSize":{"w":1791,"h":159}},{"filename":"heat0028","frame":{"x":1792,"y":640,"w":1791,"h":159},"rotated":false,"trimmed":false,"spriteSourceSize":{"x":0,"y":0,"w":1791,"h":159},"sourceSize":{"w":1791,"h":159}},{"filename":"heat0029","frame":{"x":1792,"y":800,"w":1791,"h":159},"rotated":false,"trimmed":false,"spriteSourceSize":{"x":0,"y":0,"w":1791,"h":159},"sourceSize":{"w":1791,"h":159}},{"filename":"heat0030","frame":{"x":1792,"y":960,"w":1791,"h":159},"rotated":false,"trimmed":false,"spriteSourceSize":{"x":0,"y":0,"w":1791,"h":159},"sourceSize":{"w":1791,"h":159}},{"filename":"heat0031","frame":{"x":1792,"y":1120,"w":1791,"h":159},"rotated":false,"trimmed":false,"spriteSourceSize":{"x":0,"y":0,"w":1791,"h":159},"sourceSize":{"w":1791,"h":159}},{"filename":"heat0032","frame":{"x":1792,"y":1280,"w":1791,"h":159},"rotated":false,"trimmed":false,"spriteSourceSize":{"x":0,"y":0,"w":1791,"h":159},"sourceSize":{"w":1791,"h":159}},{"filename":"heat0033","frame":{"x":1792,"y":1440,"w":1791,"h":159},"rotated":false,"trimmed":false,"spriteSourceSize":{"x":0,"y":0,"w":1791,"h":159},"sourceSize":{"w":1791,"h":159}},{"filename":"heat0034","frame":{"x":1792,"y":1600,"w":1791,"h":159},"rotated":false,"trimmed":false,"spriteSourceSize":{"x":0,"y":0,"w":1791,"h":159},"sourceSize":{"w":1791,"h":159}},{"filename":"heat0035","frame":{"x":1792,"y":1760,"w":1791,"h":159},"rotated":false,"trimmed":false,"spriteSourceSize":{"x":0,"y":0,"w":1791,"h":159},"sourceSize":{"w":1791,"h":159}},{"filename":"heat0036","frame":{"x":1792,"y":1920,"w":1791,"h":159},"rotated":false,"trimmed":false,"spriteSourceSize":{"x":0,"y":0,"w":1791,"h":159},"sourceSize":{"w":1791,"h":159}},{"filename":"heat0037","frame":{"x":1792,"y":2080,"w":1791,"h":159},"rotated":false,"trimmed":false,"spriteSourceSize":{"x":0,"y":0,"w":1791,"h":159},"sourceSize":{"w":1791,"h":159}},{"filename":"heat0038","frame":{"x":1792,"y":2240,"w":1791,"h":159},"rotated":false,"trimmed":false,"spriteSourceSize":{"x":0,"y":0,"w":1791,"h":159},"sourceSize":{"w":1791,"h":159}},{"filename":"heat0039","frame":{"x":1792,"y":2400,"w":1791,"h":159},"rotated":false,"trimmed":false,"spriteSourceSize":{"x":0,"y":0,"w":1791,"h":159},"sourceSize":{"w":1791,"h":159}},{"filename":"heat0040","frame":{"x":1792,"y":2560,"w":1791,"h":159},"rotated":false,"trimmed":false,"spriteSourceSize":{"x":0,"y":0,"w":1791,"h":159},"sourceSize":{"w":1791,"h":159}},{"filename":"heat0041","frame":{"x":1792,"y":2720,"w":1791,"h":159},"rotated":false,"trimmed":false,"spriteSourceSize":{"x":0,"y":0,"w":1791,"h":159},"sourceSize":{"w":1791,"h":159}},{"filename":"heat0042","frame":{"x":1792,"y":2880,"w":1791,"h":159},"rotated":false,"trimmed":false,"spriteSourceSize":{"x":0,"y":0,"w":1791,"h":159},"sourceSize":{"w":1791,"h":159}},{"filename":"heat0043","frame":{"x":1792,"y":3040,"w":1791,"h":159},"rotated":false,"trimmed":false,"spriteSourceSize":{"x":0,"y":0,"w":1791,"h":159},"sourceSize":{"w":1791,"h":159}},{"filename":"heat0044","frame":{"x":1792,"y":3200,"w":1791,"h":159},"rotated":false,"trimmed":false,"spriteSourceSize":{"x":0,"y":0,"w":1791,"h":159},"sourceSize":{"w":1791,"h":159}},{"filename":"heat0045","frame":{"x":1792,"y":3360,"w":1791,"h":159},"rotated":false,"trimmed":false,"spriteSourceSize":{"x":0,"y":0,"w":1791,"h":159},"sourceSize":{"w":1791,"h":159}},{"filename":"heat0046","frame":{"x":0,"y":3520,"w":1791,"h":159},"rotated":false,"trimmed":false,"spriteSourceSize":{"x":0,"y":0,"w":1791,"h":159},"sourceSize":{"w":1791,"h":159}},{"filename":"heat0047","frame":{"x":1792,"y":3520,"w":1791,"h":159},"rotated":false,"trimmed":false,"spriteSourceSize":{"x":0,"y":0,"w":1791,"h":159},"sourceSize":{"w":1791,"h":159}},{"filename":"heat0048","frame":{"x":0,"y":3680,"w":1791,"h":159},"rotated":false,"trimmed":false,"spriteSourceSize":{"x":0,"y":0,"w":1791,"h":159},"sourceSize":{"w":1791,"h":159}},{"filename":"heat0049","frame":{"x":1792,"y":3680,"w":1791,"h":159},"rotated":false,"trimmed":false,"spriteSourceSize":{"x":0,"y":0,"w":1791,"h":159},"sourceSize":{"w":1791,"h":159}},{"filename":"heat0050","frame":{"x":0,"y":3840,"w":1791,"h":159},"rotated":false,"trimmed":false,"spriteSourceSize":{"x":0,"y":0,"w":1791,"h":159},"sourceSize":{"w":1791,"h":159}},{"filename":"heat0051","frame":{"x":1792,"y":3840,"w":1791,"h":159},"rotated":false,"trimmed":false,"spriteSourceSize":{"x":0,"y":0,"w":1791,"h":159},"sourceSize":{"w":1791,"h":159}},{"filename":"heat0052","frame":{"x":0,"y":4000,"w":1791,"h":159},"rotated":false,"trimmed":false,"spriteSourceSize":{"x":0,"y":0,"w":1791,"h":159},"sourceSize":{"w":1791,"h":159}},{"filename":"heat0053","frame":{"x":1792,"y":4000,"w":1791,"h":159},"rotated":false,"trimmed":false,"spriteSourceSize":{"x":0,"y":0,"w":1791,"h":159},"sourceSize":{"w":1791,"h":159}},{"filename":"heat0054","frame":{"x":0,"y":4160,"w":1791,"h":159},"rotated":false,"trimmed":false,"spriteSourceSize":{"x":0,"y":0,"w":1791,"h":159},"sourceSize":{"w":1791,"h":159}},{"filename":"heat0055","frame":{"x":1792,"y":4160,"w":1791,"h":159},"rotated":false,"trimmed":false,"spriteSourceSize":{"x":0,"y":0,"w":1791,"h":159},"sourceSize":{"w":1791,"h":159}},{"filename":"heat0056","frame":{"x":0,"y":4320,"w":1791,"h":159},"rotated":false,"trimmed":false,"spriteSourceSize":{"x":0,"y":0,"w":1791,"h":159},"sourceSize":{"w":1791,"h":159}},{"filename":"heat0057","frame":{"x":1792,"y":4320,"w":1791,"h":159},"rotated":false,"trimmed":false,"spriteSourceSize":{"x":0,"y":0,"w":1791,"h":159},"sourceSize":{"w":1791,"h":159}},{"filename":"heat0058","frame":{"x":0,"y":4480,"w":1791,"h":159},"rotated":false,"trimmed":false,"spriteSourceSize":{"x":0,"y":0,"w":1791,"h":159},"sourceSize":{"w":1791,"h":159}},{"filename":"heat0059","frame":{"x":1792,"y":4480,"w":1791,"h":159},"rotated":false,"trimmed":false,"spriteSourceSize":{"x":0,"y":0,"w":1791,"h":159},"sourceSize":{"w":1791,"h":159}},{"filename":"heat0060","frame":{"x":0,"y":4640,"w":1791,"h":159},"rotated":false,"trimmed":false,"spriteSourceSize":{"x":0,"y":0,"w":1791,"h":159},"sourceSize":{"w":1791,"h":159}},{"filename":"heat0061","frame":{"x":1792,"y":4640,"w":1791,"h":159},"rotated":false,"trimmed":false,"spriteSourceSize":{"x":0,"y":0,"w":1791,"h":159},"sourceSize":{"w":1791,"h":159}},{"filename":"heat0062","frame":{"x":0,"y":4800,"w":1791,"h":159},"rotated":false,"trimmed":false,"spriteSourceSize":{"x":0,"y":0,"w":1791,"h":159},"sourceSize":{"w":1791,"h":159}},{"filename":"heat0063","frame":{"x":1792,"y":4800,"w":1791,"h":159},"rotated":false,"trimmed":false,"spriteSourceSize":{"x":0,"y":0,"w":1791,"h":159},"sourceSize":{"w":1791,"h":159}},{"filename":"heat0064","frame":{"x":0,"y":4960,"w":1791,"h":159},"rotated":false,"trimmed":false,"spriteSourceSize":{"x":0,"y":0,"w":1791,"h":159},"sourceSize":{"w":1791,"h":159}},{"filename":"heat0065","frame":{"x":1792,"y":4960,"w":1791,"h":159},"rotated":false,"trimmed":false,"spriteSourceSize":{"x":0,"y":0,"w":1791,"h":159},"sourceSize":{"w":1791,"h":159}},{"filename":"heat0066","frame":{"x":0,"y":5120,"w":1791,"h":159},"rotated":false,"trimmed":false,"spriteSourceSize":{"x":0,"y":0,"w":1791,"h":159},"sourceSize":{"w":1791,"h":159}},{"filename":"idle","frame":{"x":1792,"y":5120,"w":1791,"h":159},"rotated":false,"trimmed":false,"spriteSourceSize":{"x":0,"y":0,"w":1791,"h":159},"sourceSize":{"w":1791,"h":159}},{"filename":"cool0000","frame":{"x":3584,"y":0,"w":1791,"h":159},"rotated":false,"trimmed":false,"spriteSourceSize":{"x":0,"y":0,"w":1791,"h":159},"sourceSize":{"w":1791,"h":159}},{"filename":"cool0001","frame":{"x":3584,"y":160,"w":1791,"h":159},"rotated":false,"trimmed":false,"spriteSourceSize":{"x":0,"y":0,"w":1791,"h":159},"sourceSize":{"w":1791,"h":159}},{"filename":"cool0002","frame":{"x":3584,"y":320,"w":1791,"h":159},"rotated":false,"trimmed":false,"spriteSourceSize":{"x":0,"y":0,"w":1791,"h":159},"sourceSize":{"w":1791,"h":159}},{"filename":"cool0003","frame":{"x":3584,"y":480,"w":1791,"h":159},"rotated":false,"trimmed":false,"spriteSourceSize":{"x":0,"y":0,"w":1791,"h":159},"sourceSize":{"w":1791,"h":159}},{"filename":"cool0004","frame":{"x":3584,"y":640,"w":1791,"h":159},"rotated":false,"trimmed":false,"spriteSourceSize":{"x":0,"y":0,"w":1791,"h":159},"sourceSize":{"w":1791,"h":159}},{"filename":"cool0005","frame":{"x":3584,"y":800,"w":1791,"h":159},"rotated":false,"trimmed":false,"spriteSourceSize":{"x":0,"y":0,"w":1791,"h":159},"sourceSize":{"w":1791,"h":159}},{"filename":"cool0007","frame":{"x":3584,"y":960,"w":1791,"h":159},"rotated":false,"trimmed":false,"spriteSourceSize":{"x":0,"y":0,"w":1791,"h":159},"sourceSize":{"w":1791,"h":159}},{"filename":"cool0008","frame":{"x":3584,"y":1120,"w":1791,"h":159},"rotated":false,"trimmed":false,"spriteSourceSize":{"x":0,"y":0,"w":1791,"h":159},"sourceSize":{"w":1791,"h":159}},{"filename":"cool0006","frame":{"x":3584,"y":1280,"w":1791,"h":159},"rotated":false,"trimmed":false,"spriteSourceSize":{"x":0,"y":0,"w":1791,"h":159},"sourceSize":{"w":1791,"h":159}},{"filename":"cool0012","frame":{"x":3584,"y":1440,"w":1791,"h":159},"rotated":false,"trimmed":false,"spriteSourceSize":{"x":0,"y":0,"w":1791,"h":159},"sourceSize":{"w":1791,"h":159}},{"filename":"cool0009","frame":{"x":3584,"y":1600,"w":1791,"h":159},"rotated":false,"trimmed":false,"spriteSourceSize":{"x":0,"y":0,"w":1791,"h":159},"sourceSize":{"w":1791,"h":159}},{"filename":"cool0011","frame":{"x":3584,"y":1760,"w":1791,"h":159},"rotated":false,"trimmed":false,"spriteSourceSize":{"x":0,"y":0,"w":1791,"h":159},"sourceSize":{"w":1791,"h":159}},{"filename":"cool0014","frame":{"x":3584,"y":1920,"w":1791,"h":159},"rotated":false,"trimmed":false,"spriteSourceSize":{"x":0,"y":0,"w":1791,"h":159},"sourceSize":{"w":1791,"h":159}},{"filename":"cool0013","frame":{"x":3584,"y":2080,"w":1791,"h":159},"rotated":false,"trimmed":false,"spriteSourceSize":{"x":0,"y":0,"w":1791,"h":159},"sourceSize":{"w":1791,"h":159}},{"filename":"cool0010","frame":{"x":3584,"y":2240,"w":1791,"h":159},"rotated":false,"trimmed":false,"spriteSourceSize":{"x":0,"y":0,"w":1791,"h":159},"sourceSize":{"w":1791,"h":159}},{"filename":"cool0015","frame":{"x":3584,"y":2400,"w":1791,"h":159},"rotated":false,"trimmed":false,"spriteSourceSize":{"x":0,"y":0,"w":1791,"h":159},"sourceSize":{"w":1791,"h":159}},{"filename":"cool0061","frame":{"x":3584,"y":2560,"w":1791,"h":159},"rotated":false,"trimmed":false,"spriteSourceSize":{"x":0,"y":0,"w":1791,"h":159},"sourceSize":{"w":1791,"h":159}},{"filename":"cool0062","frame":{"x":3584,"y":2720,"w":1791,"h":159},"rotated":false,"trimmed":false,"spriteSourceSize":{"x":0,"y":0,"w":1791,"h":159},"sourceSize":{"w":1791,"h":159}},{"filename":"cool0016","frame":{"x":3584,"y":2880,"w":1791,"h":159},"rotated":false,"trimmed":false,"spriteSourceSize":{"x":0,"y":0,"w":1791,"h":159},"sourceSize":{"w":1791,"h":159}},{"filename":"cool0017","frame":{"x":3584,"y":3040,"w":1791,"h":159},"rotated":false,"trimmed":false,"spriteSourceSize":{"x":0,"y":0,"w":1791,"h":159},"sourceSize":{"w":1791,"h":159}},{"filename":"cool0018","frame":{"x":3584,"y":3200,"w":1791,"h":159},"rotated":false,"trimmed":false,"spriteSourceSize":{"x":0,"y":0,"w":1791,"h":159},"sourceSize":{"w":1791,"h":159}},{"filename":"cool0052","frame":{"x":3584,"y":3360,"w":1791,"h":159},"rotated":false,"trimmed":false,"spriteSourceSize":{"x":0,"y":0,"w":1791,"h":159},"sourceSize":{"w":1791,"h":159}},{"filename":"cool0051","frame":{"x":3584,"y":3520,"w":1791,"h":159},"rotated":false,"trimmed":false,"spriteSourceSize":{"x":0,"y":0,"w":1791,"h":159},"sourceSize":{"w":1791,"h":159}},{"filename":"cool0020","frame":{"x":3584,"y":3680,"w":1791,"h":159},"rotated":false,"trimmed":false,"spriteSourceSize":{"x":0,"y":0,"w":1791,"h":159},"sourceSize":{"w":1791,"h":159}},{"filename":"cool0037","frame":{"x":3584,"y":3840,"w":1791,"h":159},"rotated":false,"trimmed":false,"spriteSourceSize":{"x":0,"y":0,"w":1791,"h":159},"sourceSize":{"w":1791,"h":159}},{"filename":"cool0035","frame":{"x":3584,"y":4000,"w":1791,"h":159},"rotated":false,"trimmed":false,"spriteSourceSize":{"x":0,"y":0,"w":1791,"h":159},"sourceSize":{"w":1791,"h":159}},{"filename":"cool0033","frame":{"x":3584,"y":4160,"w":1791,"h":159},"rotated":false,"trimmed":false,"spriteSourceSize":{"x":0,"y":0,"w":1791,"h":159},"sourceSize":{"w":1791,"h":159}},{"filename":"cool0022","frame":{"x":3584,"y":4320,"w":1791,"h":159},"rotated":false,"trimmed":false,"spriteSourceSize":{"x":0,"y":0,"w":1791,"h":159},"sourceSize":{"w":1791,"h":159}},{"filename":"cool0038","frame":{"x":3584,"y":4480,"w":1791,"h":159},"rotated":false,"trimmed":false,"spriteSourceSize":{"x":0,"y":0,"w":1791,"h":159},"sourceSize":{"w":1791,"h":159}},{"filename":"cool0048","frame":{"x":3584,"y":4640,"w":1791,"h":159},"rotated":false,"trimmed":false,"spriteSourceSize":{"x":0,"y":0,"w":1791,"h":159},"sourceSize":{"w":1791,"h":159}},{"filename":"cool0034","frame":{"x":3584,"y":4800,"w":1791,"h":159},"rotated":false,"trimmed":false,"spriteSourceSize":{"x":0,"y":0,"w":1791,"h":159},"sourceSize":{"w":1791,"h":159}},{"filename":"cool0026","frame":{"x":3584,"y":4960,"w":1791,"h":159},"rotated":false,"trimmed":false,"spriteSourceSize":{"x":0,"y":0,"w":1791,"h":159},"sourceSize":{"w":1791,"h":159}},{"filename":"cool0043","frame":{"x":3584,"y":5120,"w":1791,"h":159},"rotated":false,"trimmed":false,"spriteSourceSize":{"x":0,"y":0,"w":1791,"h":159},"sourceSize":{"w":1791,"h":159}},{"filename":"cool0050","frame":{"x":0,"y":5280,"w":1791,"h":159},"rotated":false,"trimmed":false,"spriteSourceSize":{"x":0,"y":0,"w":1791,"h":159},"sourceSize":{"w":1791,"h":159}},{"filename":"cool0049","frame":{"x":1792,"y":5280,"w":1791,"h":159},"rotated":false,"trimmed":false,"spriteSourceSize":{"x":0,"y":0,"w":1791,"h":159},"sourceSize":{"w":1791,"h":159}},{"filename":"cool0054","frame":{"x":3584,"y":5280,"w":1791,"h":159},"rotated":false,"trimmed":false,"spriteSourceSize":{"x":0,"y":0,"w":1791,"h":159},"sourceSize":{"w":1791,"h":159}},{"filename":"cool0040","frame":{"x":0,"y":5440,"w":1791,"h":159},"rotated":false,"trimmed":false,"spriteSourceSize":{"x":0,"y":0,"w":1791,"h":159},"sourceSize":{"w":1791,"h":159}},{"filename":"cool0021","frame":{"x":1792,"y":5440,"w":1791,"h":159},"rotated":false,"trimmed":false,"spriteSourceSize":{"x":0,"y":0,"w":1791,"h":159},"sourceSize":{"w":1791,"h":159}},{"filename":"cool0047","frame":{"x":3584,"y":5440,"w":1791,"h":159},"rotated":false,"trimmed":false,"spriteSourceSize":{"x":0,"y":0,"w":1791,"h":159},"sourceSize":{"w":1791,"h":159}},{"filename":"cool0023","frame":{"x":0,"y":5600,"w":1791,"h":159},"rotated":false,"trimmed":false,"spriteSourceSize":{"x":0,"y":0,"w":1791,"h":159},"sourceSize":{"w":1791,"h":159}},{"filename":"cool0024","frame":{"x":1792,"y":5600,"w":1791,"h":159},"rotated":false,"trimmed":false,"spriteSourceSize":{"x":0,"y":0,"w":1791,"h":159},"sourceSize":{"w":1791,"h":159}},{"filename":"cool0039","frame":{"x":3584,"y":5600,"w":1791,"h":159},"rotated":false,"trimmed":false,"spriteSourceSize":{"x":0,"y":0,"w":1791,"h":159},"sourceSize":{"w":1791,"h":159}},{"filename":"cool0053","frame":{"x":0,"y":5760,"w":1791,"h":159},"rotated":false,"trimmed":false,"spriteSourceSize":{"x":0,"y":0,"w":1791,"h":159},"sourceSize":{"w":1791,"h":159}},{"filename":"cool0045","frame":{"x":1792,"y":5760,"w":1791,"h":159},"rotated":false,"trimmed":false,"spriteSourceSize":{"x":0,"y":0,"w":1791,"h":159},"sourceSize":{"w":1791,"h":159}},{"filename":"cool0019","frame":{"x":3584,"y":5760,"w":1791,"h":159},"rotated":false,"trimmed":false,"spriteSourceSize":{"x":0,"y":0,"w":1791,"h":159},"sourceSize":{"w":1791,"h":159}},{"filename":"cool0041","frame":{"x":0,"y":5920,"w":1791,"h":159},"rotated":false,"trimmed":false,"spriteSourceSize":{"x":0,"y":0,"w":1791,"h":159},"sourceSize":{"w":1791,"h":159}},{"filename":"cool0042","frame":{"x":1792,"y":5920,"w":1791,"h":159},"rotated":false,"trimmed":false,"spriteSourceSize":{"x":0,"y":0,"w":1791,"h":159},"sourceSize":{"w":1791,"h":159}},{"filename":"cool0056","frame":{"x":3584,"y":5920,"w":1791,"h":159},"rotated":false,"trimmed":false,"spriteSourceSize":{"x":0,"y":0,"w":1791,"h":159},"sourceSize":{"w":1791,"h":159}},{"filename":"cool0032","frame":{"x":0,"y":6080,"w":1791,"h":159},"rotated":false,"trimmed":false,"spriteSourceSize":{"x":0,"y":0,"w":1791,"h":159},"sourceSize":{"w":1791,"h":159}},{"filename":"cool0046","frame":{"x":1792,"y":6080,"w":1791,"h":159},"rotated":false,"trimmed":false,"spriteSourceSize":{"x":0,"y":0,"w":1791,"h":159},"sourceSize":{"w":1791,"h":159}},{"filename":"cool0028","frame":{"x":3584,"y":6080,"w":1791,"h":159},"rotated":false,"trimmed":false,"spriteSourceSize":{"x":0,"y":0,"w":1791,"h":159},"sourceSize":{"w":1791,"h":159}},{"filename":"cool0025","frame":{"x":0,"y":6240,"w":1791,"h":159},"rotated":false,"trimmed":false,"spriteSourceSize":{"x":0,"y":0,"w":1791,"h":159},"sourceSize":{"w":1791,"h":159}},{"filename":"cool0030","frame":{"x":1792,"y":6240,"w":1791,"h":159},"rotated":false,"trimmed":false,"spriteSourceSize":{"x":0,"y":0,"w":1791,"h":159},"sourceSize":{"w":1791,"h":159}},{"filename":"cool0036","frame":{"x":3584,"y":6240,"w":1791,"h":159},"rotated":false,"trimmed":false,"spriteSourceSize":{"x":0,"y":0,"w":1791,"h":159},"sourceSize":{"w":1791,"h":159}},{"filename":"cool0027","frame":{"x":0,"y":6400,"w":1791,"h":159},"rotated":false,"trimmed":false,"spriteSourceSize":{"x":0,"y":0,"w":1791,"h":159},"sourceSize":{"w":1791,"h":159}},{"filename":"cool0044","frame":{"x":1792,"y":6400,"w":1791,"h":159},"rotated":false,"trimmed":false,"spriteSourceSize":{"x":0,"y":0,"w":1791,"h":159},"sourceSize":{"w":1791,"h":159}},{"filename":"cool0031","frame":{"x":3584,"y":6400,"w":1791,"h":159},"rotated":false,"trimmed":false,"spriteSourceSize":{"x":0,"y":0,"w":1791,"h":159},"sourceSize":{"w":1791,"h":159}},{"filename":"cool0029","frame":{"x":0,"y":6560,"w":1791,"h":159},"rotated":false,"trimmed":false,"spriteSourceSize":{"x":0,"y":0,"w":1791,"h":159},"sourceSize":{"w":1791,"h":159}},{"filename":"cool0055","frame":{"x":1792,"y":6560,"w":1791,"h":159},"rotated":false,"trimmed":false,"spriteSourceSize":{"x":0,"y":0,"w":1791,"h":159},"sourceSize":{"w":1791,"h":159}},{"filename":"cool0057","frame":{"x":3584,"y":6560,"w":1791,"h":159},"rotated":false,"trimmed":false,"spriteSourceSize":{"x":0,"y":0,"w":1791,"h":159},"sourceSize":{"w":1791,"h":159}},{"filename":"cool0058","frame":{"x":0,"y":6720,"w":1791,"h":159},"rotated":false,"trimmed":false,"spriteSourceSize":{"x":0,"y":0,"w":1791,"h":159},"sourceSize":{"w":1791,"h":159}},{"filename":"cool0059","frame":{"x":1792,"y":6720,"w":1791,"h":159},"rotated":false,"trimmed":false,"spriteSourceSize":{"x":0,"y":0,"w":1791,"h":159},"sourceSize":{"w":1791,"h":159}},{"filename":"cool0060","frame":{"x":3584,"y":6720,"w":1791,"h":159},"rotated":false,"trimmed":false,"spriteSourceSize":{"x":0,"y":0,"w":1791,"h":159},"sourceSize":{"w":1791,"h":159}},{"filename":"cool0063","frame":{"x":0,"y":6880,"w":1791,"h":159},"rotated":false,"trimmed":false,"spriteSourceSize":{"x":0,"y":0,"w":1791,"h":159},"sourceSize":{"w":1791,"h":159}},{"filename":"cool0064","frame":{"x":1792,"y":6880,"w":1791,"h":159},"rotated":false,"trimmed":false,"spriteSourceSize":{"x":0,"y":0,"w":1791,"h":159},"sourceSize":{"w":1791,"h":159}},{"filename":"cool0065","frame":{"x":3584,"y":6880,"w":1791,"h":159},"rotated":false,"trimmed":false,"spriteSourceSize":{"x":0,"y":0,"w":1791,"h":159},"sourceSize":{"w":1791,"h":159}},{"filename":"cool0066","frame":{"x":5376,"y":0,"w":1791,"h":159},"rotated":false,"trimmed":false,"spriteSourceSize":{"x":0,"y":0,"w":1791,"h":159},"sourceSize":{"w":1791,"h":159}},{"filename":"heat0000","frame":{"x":5376,"y":160,"w":1791,"h":159},"rotated":false,"trimmed":false,"spriteSourceSize":{"x":0,"y":0,"w":1791,"h":159},"sourceSize":{"w":1791,"h":159}},{"filename":"heat0001","frame":{"x":5376,"y":320,"w":1791,"h":159},"rotated":false,"trimmed":false,"spriteSourceSize":{"x":0,"y":0,"w":1791,"h":159},"sourceSize":{"w":1791,"h":159}}],"meta":{"app":"https://www.leshylabs.com/apps/sstool/","version":"Leshy SpriteSheet Tool v0.8.4","image":"temperature_bg.png","size":{"w":7167,"h":7039},"scale":1}}