{
"skeleton": {
	"hash": "7hNndIPaBLA",
	"spine": "4.2.36",
	"x": -425.04,
	"y": -236.2,
	"width": 901.6,
	"height": 543.96,
	"images": "./Parts/",
	"audio": "C:/Users/antsg/OneDrive/Documents/Bella Sara Shennanigans/stables game/images/horse/peter"
},
"bones": [
	{ "name": "root", "length": 40, "rotation": -90, "x": 68.7, "y": 65.07 },
	{ "name": "Body", "parent": "root", "length": 160, "rotation": -83.91, "x": 25.41, "y": -6.03 }
],
"slots": [
	{ "name": "Body", "bone": "Body", "attachment": "Body" }
],
"skins": [
	{
		"name": "default",
		"attachments": {
			"Body": {
				"Body": { "x": 34.96, "y": 0.94, "rotation": 173.94, "width": 888, "height": 521 }
			}
		}
	}
],
"animations": {
	"drink": {
		"bones": {
			"Body": {
				"rotate": [
					{ "time": 0.0333 },
					{ "time": 0.6667, "value": 3.1, "curve": "stepped" },
					{ "time": 2.2, "value": 3.1 },
					{ "time": 2.6 }
				],
				"translate": [
					{ "time": 0.0333 },
					{ "time": 0.6667, "x": -4.85, "y": 6.67, "curve": "stepped" },
					{ "time": 2.2, "x": -4.85, "y": 6.67 },
					{ "time": 2.6 }
				]
			}
		}
	},
	"ear_twitch": {
		"bones": {
			"Body": {
				"translate": [
					{ "time": 0.3333 }
				]
			}
		}
	},
	"eat_apple": {
		"bones": {
			"Body": {
				"rotate": [
					{ "time": 0.0667 },
					{ "time": 0.3333, "value": 1.51, "curve": "stepped" },
					{ "time": 2.0333, "value": 1.51 },
					{ "time": 2.5 }
				],
				"translate": [
					{ "time": 0.0667 },
					{ "time": 0.3333, "x": -1.54, "y": -10.17, "curve": "stepped" },
					{ "time": 2.0333, "x": -1.54, "y": -10.17 },
					{ "time": 2.5, "curve": "stepped" },
					{ "time": 2.6667 }
				]
			}
		}
	},
	"eat_food": {
		"bones": {
			"Body": {
				"translate": [
					{ "time": 0.0667 },
					{ "time": 0.3, "x": 0.69, "y": -10, "curve": "stepped" },
					{ "time": 1.9667, "x": 0.69, "y": -10 },
					{ "time": 2.5 }
				]
			}
		}
	},
	"flank_twitch": {
		"bones": {
			"Body": {
				"rotate": [
					{ "time": 0.0667 },
					{ "time": 1, "value": 0.96 },
					{ "time": 1.9333 }
				],
				"translate": [
					{ "time": 0.0667 },
					{ "time": 1, "x": 0.59, "y": -2.94 },
					{ "time": 1.9333, "curve": "stepped" },
					{ "time": 2 }
				]
			}
		}
	},
	"head_shake": {
		"bones": {
			"Body": {
				"translate": [
					{ "time": 1.8333 }
				]
			}
		}
	},
	"head_turn": {
		"bones": {
			"Body": {
				"translate": [
					{ "time": 2.6667 }
				]
			}
		}
	},
	"idle": {
		"bones": {
			"Body": {
				"translate": [
					{}
				]
			}
		}
	},
	"nod": {
		"bones": {
			"Body": {
				"translate": [
					{ "time": 0.6667 }
				]
			}
		}
	},
	"paw_ground": {
		"bones": {
			"Body": {
				"rotate": [
					{},
					{ "time": 0.5333, "value": 0.74 },
					{ "time": 1 }
				]
			}
		}
	},
	"rear": {
		"bones": {
			"Body": {
				"rotate": [
					{},
					{ "time": 0.2, "value": 4.68 },
					{ "time": 0.2333, "value": 2.65 },
					{ "time": 0.2667, "value": -2.84 },
					{ "time": 0.3, "value": -13.07 },
					{ "time": 0.3667, "value": -25.12 },
					{ "time": 0.4, "value": -33.62 },
					{ "time": 0.4333, "value": -39.27 },
					{ "time": 0.5, "value": -41.16, "curve": "stepped" },
					{ "time": 0.9333, "value": -41.16 },
					{ "time": 1, "value": -35.74 },
					{ "time": 1.0667, "value": -32.19 },
					{ "time": 1.1, "value": -24.79 },
					{ "time": 1.1333, "value": -16.69 },
					{ "time": 1.2, "value": -7.24 },
					{ "time": 1.2333, "value": 5.13 },
					{ "time": 1.5333 }
				],
				"translate": [
					{},
					{ "time": 0.2, "x": 1.15, "y": 4.01 },
					{ "time": 0.3, "x": -0.07, "y": 16.74 },
					{ "time": 0.3667, "x": -1.41, "y": 20.48 },
					{ "time": 0.4333, "x": -4.85, "y": 22.27 },
					{ "time": 0.5, "x": -3.45, "y": 24.07 },
					{ "time": 0.6333, "x": -4.6, "y": 24.93 },
					{ "time": 0.9333, "x": -3.45, "y": 24.07 },
					{ "time": 1, "x": -4.6, "y": 24.88 },
					{ "time": 1.1, "x": -3.12, "y": 17.55 },
					{ "time": 1.2, "x": -1.03, "y": 13.13 },
					{ "time": 1.2333, "x": -0.69, "y": 3.79 },
					{ "time": 1.5333 }
				]
			}
		}
	},
	"shift_weight": {
		"bones": {
			"Body": {
				"rotate": [
					{},
					{ "time": 0.3333, "value": -1.65 },
					{ "time": 0.6667 }
				],
				"translate": [
					{},
					{ "time": 0.3333, "x": 2.88, "y": 5.52 },
					{ "time": 0.6667, "curve": "stepped" },
					{ "time": 1.6667 }
				]
			}
		}
	},
	"tail_swish": {
		"bones": {
			"Body": {
				"translate": [
					{ "time": 0.6667 }
				]
			}
		}
	}
}
}